LICENSE
MANIFEST.in
README.rst
requirements.txt
setup.py
test_threetaps.py
threetaps/__init__.py
threetaps/client.py
threetaps.egg-info/PKG-INFO
threetaps.egg-info/SOURCES.txt
threetaps.egg-info/dependency_links.txt
threetaps.egg-info/requires.txt
threetaps.egg-info/top_level.txt