Metadata-Version: 1.0
Name: threetaps
Version: 0.1.4
Summary: 3taps API Client.
Home-page: https://github.com/mkolodny/3taps
Author: Michael Kolodny
Author-email: michaelckolodny@gmail.com
License: The MIT License (MIT)
